caffe/__init__.py
caffe/_caffe.cp38-win_amd64.pyd
caffe/classifier.py
caffe/coord_map.py
caffe/detector.py
caffe/draw.py
caffe/io.py
caffe/net_spec.py
caffe/pycaffe.py
caffe/proto/__init__.py
caffe/proto/caffe_pb2.py
kendryte_caffe-1.0.0.20210829.dist-info/LICENSE
kendryte_caffe-1.0.0.20210829.dist-info/METADATA
kendryte_caffe-1.0.0.20210829.dist-info/WHEEL
kendryte_caffe-1.0.0.20210829.dist-info/top_level.txt
kendryte_caffe-1.0.0.20210829.dist-info/RECORD
