Metadata-Version: 2.1
Name: kendryte-caffe
Version: 1.0.0.20210829
Summary: Caffe: a fast open framework for deep learning.
Home-page: https://github.com/kendryte/caffe
Author: sunnycase
Author-email: sunnycase@live.cn
Maintainer: sunnycase
License: UNKNOWN
Keywords: kendryte,caffe
Platform: UNKNOWN
Classifier: Programming Language :: C++
Classifier: Programming Language :: Python :: 3
Classifier: Programming Language :: Python :: 3.6
Classifier: Programming Language :: Python :: 3.7
Classifier: Programming Language :: Python :: 3.8
Classifier: Programming Language :: Python :: 3.9
Classifier: Operating System :: OS Independent
Requires-Python: >=3.6
License-File: LICENSE
Requires-Dist: numpy (>=1.7.1)
Requires-Dist: scipy (>=0.13.2)
Requires-Dist: scikit-image (>=0.9.3)
Requires-Dist: protobuf (>=2.5.0)
Requires-Dist: six (>=1.1.0)
